setup.py
flask_lesscss.egg-info/PKG-INFO
flask_lesscss.egg-info/SOURCES.txt
flask_lesscss.egg-info/dependency_links.txt
flask_lesscss.egg-info/namespace_packages.txt
flask_lesscss.egg-info/not-zip-safe
flask_lesscss.egg-info/requires.txt
flask_lesscss.egg-info/top_level.txt
flaskext/__init__.py
flaskext/lesscss.py