Metadata-Version: 1.0
Name: flask-lesscss
Version: 0.9.1
Summary: A small Flask extension that adds LessCSS support to Flask.
Home-page: http://sjl.bitbucket.org/flask-lesscss/
Author: Steve Losh
Author-email: steve@stevelosh.com
License: MIT
Platform: any
Classifier: Development Status :: 4 - Beta
Classifier: Environment :: Web Environment
Classifier: Intended Audience :: Developers
Classifier: License :: OSI Approved :: MIT License
Classifier: Operating System :: OS Independent
Classifier: Programming Language :: Python
Classifier: Topic :: Internet :: WWW/HTTP :: Dynamic Content
Classifier: Topic :: Software Development :: Libraries :: Python Modules
